README.rst
setup.py
docs/HISTORY.rst
src/pikacon/__init__.py
src/pikacon/binding.py
src/pikacon/config.py
src/pikacon/exchange.py
src/pikacon/pikacon.py
src/pikacon/queue.py
src/pikacon.egg-info/PKG-INFO
src/pikacon.egg-info/SOURCES.txt
src/pikacon.egg-info/dependency_links.txt
src/pikacon.egg-info/not-zip-safe
src/pikacon.egg-info/requires.txt
src/pikacon.egg-info/top_level.txt
tests/__init__.py
tests/test_config.cfg
tests/test_config.py