Metadata-Version: 1.0
Name: pikacon
Version: 0.3.1
Summary: Helper library for using pika.
Home-page: https://github.com/pingviini/pikacon
Author: Jukka Ojaniemi
Author-email: jukka.ojaniemi@jyu.fi
License: GPL
Platform: UNKNOWN
Classifier: Programming Language :: Python :: 2.6
Classifier: Programming Language :: Python :: 2.7
